{
  "parent": "minecraft:recipes/root",
  "rewards": {
    "recipes": [
      "totemic:flute"
    ]
  },
  "criteria": {
    "has_totempedia": {
      "trigger": "minecraft:inventory_changed",
      "conditions": {
        "items": [
          {
            "items": [
              "patchouli:guide_book"
            ],
            "nbt": "{\"patchouli:book\":\"totemic:totempedia\"}"
          }
        ]
      }
    },
    "has_the_recipe": {
      "trigger": "minecraft:recipe_unlocked",
      "conditions": {
        "recipe": "totemic:flute"
      }
    }
  },
  "requirements": [
    [
      "has_totempedia",
      "has_the_recipe"
    ]
  ]
}