{
  "parent": "minecraft:recipes/root",
  "criteria": {
    "has_jingle_dress_recipe": {
      "conditions": {
        "recipe": "totemic:jingle_dress"
      },
      "trigger": "minecraft:recipe_unlocked"
    },
    "has_the_recipe": {
      "conditions": {
        "recipe": "totemic:iron_bells"
      },
      "trigger": "minecraft:recipe_unlocked"
    }
  },
  "requirements": [
    [
      "has_the_recipe",
      "has_jingle_dress_recipe"
    ]
  ],
  "rewards": {
    "recipes": [
      "totemic:iron_bells"
    ]
  },
  "sends_telemetry_event": false
}