{
  "parent": "totemic:recipes/root",
  "rewards": {
    "recipes": [
      "totemic:drum"
    ]
  },
  "criteria": {
    "has_totempedia": {
      "trigger": "minecraft:inventory_changed",
      "conditions": {
        "items": [
          {
            "item": "totemic:totempedia"
          }
        ]
      }
    },
    "has_the_recipe": {
      "trigger": "minecraft:recipe_unlocked",
      "conditions": {
        "recipe": "totemic:drum"
      }
    }
  },
  "requirements": [
    [
      "has_totempedia",
      "has_the_recipe"
    ]
  ]
}
